[
  {
    "_id": 1,
    "title": "Python Programming",
    "description": "Become a Python pro, covering basics to advanced.",
    "level": "Intermediate",
    "category": "Computer Science",
    "rating": 3,
    "img": "./assets/courseimg/python_programming.jpg",
    "trailer": "https://www.youtube.com/embed/_uQrJ0TkZlc",
    "status": "Ongoing",
    "active": true
  },
  {
    "_id": 2,
    "title": "Digital Marketing",
    "description": "Increase your business sales using digital marketing.",
    "level": "Basic",
    "category": "Computer Science",
    "rating": 3,
    "img": "./assets/courseimg/digital_marketing.jpg",
    "trailer": "https://www.youtube.com/embed/dS0PtshQDls",
    "status": "Ongoing",
    "active": false
  },
  {
    "_id": 3,
    "title": "Advanced DS with Python",
    "description": "Master data analysis using Python and open tools.",
    "level": "Intermediate",
    "category": "Computer Science",
    "rating": 4,
    "img": "./assets/courseimg/ds_python.jpg",
    "trailer": "https://www.youtube.com/embed/r-uOLxNrNk8",
    "status": "Ongoing",
    "active": false
  },
  {
    "_id": 4,
    "title": "Graphic Design",
    "description": "Learn theoretical and practical graphic design.",
    "level": "Basic",
    "category": "Computer Science",
    "rating": 5,
    "img": "./assets/courseimg/graphic_design.jpg",
    "trailer": "https://www.youtube.com/embed/5_FLHvq4Wwg",
    "status": "Ongoing",
    "active": false
  },
  {
    "_id": 5,
    "title": "Web Development",
    "description": "Step-by-step web development tutorial in Hindi.",
    "level": "Advanced",
    "category": "Computer Science",
    "rating": 4,
    "img": "./assets/courseimg/webdev.jpg",
    "trailer": "https://www.youtube.com/embed/tVzUXW6siu0",
    "status": "Ongoing",
    "active": false
  },
  {
    "_id": 6,
    "title": "Cybersecurity Essentials",
    "description": "Basics of cybersecurity and its importance.",
    "level": "Intermediate",
    "category": "Computer Science",
    "rating": 4,
    "img": "./assets/courseimg/cs_essentials.jpg",
    "trailer": "https://www.youtube.com/embed/GFHZrerq178",
    "status": "Ongoing",
    "active": false
  },
  {
    "_id": 7,
    "title": "Introduction to Cloud Computing",
    "description": "Learn the fundamentals of cloud computing.",
    "level": "Basic",
    "category": "Computer Science",
    "rating": 3,
    "img": "./assets/courseimg/cloud_computing.jpg",
    "trailer": "https://www.youtube.com/embed/HhStJ7FDBpc",
    "status": "Ongoing",
    "active": false
  },
  {
    "_id": 8,
    "title": "Mastering Machine Learning",
    "description": "Introduction to machine learning techniques.",
    "level": "Advanced",
    "category": "Computer Science",
    "rating": 5,
    "img": "./assets/courseimg/machine_learning.jpg",
    "trailer": "https://www.youtube.com/embed/Y4qO9unerGs",
    "status": "Ongoing",
    "active": false
  },
  {
    "_id": 9,
    "title": "Physics Crash Course",
    "description": "Learn the fundamentals of physics mechanics.",
    "level": "Advanced",
    "category": "Science",
    "rating": 5,
    "img": "./assets/courseimg/phy_cc.jpg",
    "trailer": "https://www.youtube.com/embed/OoO5d5P0Jn4",
    "status": "Ongoing",
    "active": false
  },
  {
    "_id": 10,
    "title": "Compiler Design",
    "description": "Understand compiler design structure and process.",
    "level": "Advanced",
    "category": "Computer Science",
    "rating": 5,
    "img": "./assets/courseimg/compiler_neso.jpg",
    "trailer": "https://www.youtube.com/embed/5ZmFlxrNaN8",
    "status": "Ongoing",
    "active": false
  },
  {
    "_id": 11,
    "title": "Principles of Chemistry",
    "description": "Basics of chemical principles by Prof. Drennan.",
    "level": "Advanced",
    "category": "Science",
    "rating": 5,
    "img": "./assets/courseimg/chem.jpg",
    "trailer": "https://www.youtube.com/embed/YkYeYhXUeEE",
    "status": "Ongoing",
    "active": false
  },
  {
    "_id": 12,
    "title": "Algebra 1M",
    "description": "International algebra course by Dr. Aviv Censor.",
    "level": "Advanced",
    "category": "Maths",
    "rating": 5,
    "img": "./assets/courseimg/algebra.jpg",
    "trailer": "https://www.youtube.com/embed/aefKXYYXT6I",
    "status": "Ongoing",
    "active": false
  },
  {
    "_id": 13,
    "title": "GED Reading Language Arts",
    "description": "Grammar and language study with David Rheinstrom.",
    "level": "Advanced",
    "category": "Language Arts",
    "rating": 5,
    "img": "./assets/courseimg/language_ged.jpg",
    "trailer": "https://www.youtube.com/embed/O-6q-siuMik",
    "status": "Ongoing",
    "active": false
  },
  {
    "_id": 14,
    "title": "Learn French from Zero",
    "description": "Start your first conversations in French today.",
    "level": "Advanced",
    "category": "Language Arts",
    "rating": 5,
    "img": "./assets/courseimg/french.jpg",
    "trailer": "https://www.youtube.com/embed/Sk6YQynZ1h8",
    "status": "Ongoing",
    "active": false
  },
  {
    "_id": 15,
    "title": "Differential and Integral Calculus 1",
    "description": "Learn calculus with Dr. Aviv Censor's course.",
    "level": "Advanced",
    "category": "Maths",
    "rating": 5,
    "img": "./assets/courseimg/calculus.jpg",
    "trailer": "https://www.youtube.com/embed/E-n78C_-biI",
    "status": "Ongoing",
    "active": false
  },
  {
    "_id": 16,
    "title": "The Early Middle Ages, 284--1000",
    "description": "Major developments in Western European history.",
    "level": "Advanced",
    "category": "History",
    "rating": 5,
    "img": "./assets/courseimg/middle_ages.jpg",
    "trailer": "https://www.youtube.com/embed/ZC8JcWVRFp8",
    "status": "Ongoing",
    "active": false
  },
  {
    "_id": 17,
    "title": "History of the World to 1500 CE",
    "description": "Narrative of world history up to 1500 CE.",
    "level": "Advanced",
    "category": "History",
    "rating": 5,
    "img": "./assets/courseimg/history_world.jpg",
    "trailer": "https://www.youtube.com/embed/r_w7pfulsn8",
    "status": "Ongoing",
    "active": false
  }
]
